Inti-0.0.0a0.data/scripts/inti_elastic_docker
Inti-0.0.0a0.data/scripts/inti_maesloader
Inti-0.0.0a0.data/scripts/inti_maloader
inti/__init__.py
inti/MA/MAAdvanced.py
inti/MA/MABase.py
inti/MA/MAESLoader.py
inti/MA/MAExecutor.py
inti/MA/MALoader.py
inti/MA/MAMag.py
inti/MA/MAMetadata.py
inti/MA/MANlp.py
inti/MA/__init__.py
Inti-0.0.0a0.dist-info/METADATA
Inti-0.0.0a0.dist-info/WHEEL
Inti-0.0.0a0.dist-info/top_level.txt
Inti-0.0.0a0.dist-info/RECORD
