Metadata-Version: 2.1
Name: Inti
Version: 0.0.0a0
Summary: Bibliographic capture system for non-scrapping data sources
Home-page: https://github.com/colav/Inti
Author: Colav
Author-email: colav@udea.edu.co
License: BSD
Platform: UNKNOWN
Requires-Dist: pymongo
Requires-Dist: numpy
Requires-Dist: requests
Requires-Dist: psutil
Requires-Dist: elasticsearch
Requires-Dist: joblib
